Cryptomamy_kraken_api/__init__.py
Cryptomamy_kraken_api/kraken_api.py
Cryptomamy_kraken_api/version.py
Cryptomamy_kraken_api-1.0.0.dist-info/LICENSE-GPLv3.txt
Cryptomamy_kraken_api-1.0.0.dist-info/LICENSE.txt
Cryptomamy_kraken_api-1.0.0.dist-info/METADATA
Cryptomamy_kraken_api-1.0.0.dist-info/WHEEL
Cryptomamy_kraken_api-1.0.0.dist-info/top_level.txt
Cryptomamy_kraken_api-1.0.0.dist-info/RECORD
