Metadata-Version: 2.1
Name: Cryptomamy_kraken_api
Version: 1.0.0
Summary: kraken.com cryptocurrency exchange API
Home-page: https://github.com/Cryptomamy/Cryptomamy_kraken_api
Author: Cryptomamy
Author-email: cryptomamy@protonmail.com
Classifier: Programming Language :: Python :: 3
Classifier: Programming Language :: Python :: 3.3
Classifier: Programming Language :: Python :: 3.4
Classifier: Programming Language :: Python :: 3.5
Classifier: Programming Language :: Python :: 3.6
Classifier: Programming Language :: Python :: 3.7
Classifier: Programming Language :: Python :: 3.8
Classifier: Programming Language :: Python :: 3.9
Classifier: Programming Language :: Python :: 3.10
Requires-Python: >=3.3
License-File: LICENSE-GPLv3.txt
License-File: LICENSE.txt
Requires-Dist: requests <3,>=2.18.2
